api_spotify/__init__.py
api_spotify/api.py
api_spotify/decorators/__init__.py
api_spotify/decorators/login.py
api_spotify/exceptions/__init__.py
api_spotify/exceptions/link.py
api_spotify/py.typed
api_spotify/types/__init__.py
api_spotify/types/album.py
api_spotify/types/artist.py
api_spotify/types/copyright.py
api_spotify/types/external_ids.py
api_spotify/types/external_urls.py
api_spotify/types/followers.py
api_spotify/types/image.py
api_spotify/types/linked_from.py
api_spotify/types/new_releases.py
api_spotify/types/owner.py
api_spotify/types/playlist.py
api_spotify/types/restrictions.py
api_spotify/types/shorts.py
api_spotify/types/token.py
api_spotify/types/track.py
api_spotify/utils.py
api_spotify-0.0.1b6.dist-info/METADATA
api_spotify-0.0.1b6.dist-info/WHEEL
api_spotify-0.0.1b6.dist-info/RECORD
