Metadata-Version: 2.1
Name: api-spotify
Version: 0.0.1b6
Summary: Wrapper for spotify APIs
Author: An0nimia
Author-email: an0nimia@protonmail.com
Requires-Python: >=3.12,<4.0
Classifier: Programming Language :: Python :: 3
Classifier: Programming Language :: Python :: 3.12
Classifier: Programming Language :: Python :: 3.13
Requires-Dist: pydantic (>=2.7.4,<3.0.0)
Requires-Dist: requests (>=2.32.3,<3.0.0)
